Test1_CRMA/__init__.py
Test1_CRMA/dataset_metadata.py
Test1_CRMA-0.4.dist-info/LICENSE.txt
Test1_CRMA-0.4.dist-info/METADATA
Test1_CRMA-0.4.dist-info/WHEEL
Test1_CRMA-0.4.dist-info/top_level.txt
Test1_CRMA-0.4.dist-info/RECORD
